tl_scripts/__init__.py
tl_scripts/copy_kibana_objects.py
tl_scripts_cli.py
tl_scripts-0.1.1.dist-info/entry_points.txt
tl_scripts-0.1.1.dist-info/WHEEL
tl_scripts-0.1.1.dist-info/METADATA
tl_scripts-0.1.1.dist-info/RECORD
