Metadata-Version: 2.1
Name: tl-scripts
Version: 0.1.1
Summary: 
Author: dorhar
Author-email: doron.harnoy@tensorleap.ai
Requires-Python: >=3.6,<4.0
Classifier: Programming Language :: Python :: 3
Classifier: Programming Language :: Python :: 3.10
Classifier: Programming Language :: Python :: 3.6
Classifier: Programming Language :: Python :: 3.7
Classifier: Programming Language :: Python :: 3.8
Classifier: Programming Language :: Python :: 3.9
Requires-Dist: docopt (>=0.6.2,<0.7.0)
Requires-Dist: ndjson (>=0.3.1,<0.4.0)
Requires-Dist: pexpect (>=4.8.0,<5.0.0)
Requires-Dist: requests (>=2.27.1,<3.0.0)
